Workbook
Name printjob: print_history!$A$2:$N$1021
Name Материалы: Материалы!$A$3:$D$9

Sheet Калькулятор печати
A1: Наценка на прибыль | B1: 0.8 | D1: knife-sharpener_NIT-PETG-B3_3h54m.gcode | H1: =VLOOKUP('Калькулятор печати'!D1,printjob,3,0) -> completed
A2: Наценка на развитие | B2: 0.35 | D2: =VLOOKUP('Калькулятор печати'!D1,printjob,12,0) -> 0
A3: Доп. 1 | B3: 100 | D3: Стоимость электроэнергии кВт, ₽ | E3: 7.08 | F3: Время моделирования, час | G3: 0 | H3: Начало печати
A4: Доп. 2 | B4: 0 | D4: Стоимость материала, ₽\кг | E4: =VLOOKUP(G9,Материалы!A2:D90,2,0) -> 869 | F4: Время подготовки, час | G4: 0.0069444444 | H4: =VLOOKUP('Калькулятор печати'!D1,printjob,4,0) -> 46053.629
A5: Доп. 3 | B5: 0 | D5: Стоимость дополнительных материалов, ₽ | E5: 50 | F5: Время печати, час | G5: =VLOOKUP('Калькулятор печати'!D1,printjob,9,0) -> 0.1621412 | H5: Окончание печати
A6: Первоначальная стоимость оборудования, ₽ | B6: 47454 | D6: Стоимость работы оператора, ₽\час | E6: 100 | F6: Время постобработки, час | G6: 0.041666667 | H6: =VLOOKUP('Калькулятор печати'!D1,printjob,5,0) -> 46053.792
A7: Срок полезного использования, лет | B7: 3 | D7: Стоимость работы дизайнера, ₽\час | E7: 600 | F7: Вес изделия, г | G7: =VLOOKUP('Калькулятор печати'!D1,printjob,11,0) -> 134.94029
A8: Годовая норма амортизации | B8: =100%*1/B7 -> 0.33333333 | D8: Стоимость готовой модели, ₽ | E8: 0 | F8: Длина использованного материала, м | G8: =VLOOKUP('Калькулятор печати'!D1,printjob,10,0) -> 45.611101
A9: Ежегодная сумма амортизации, ₽ | B9: =B6*B8 -> 15818 | D9: Потребляемая мощность оборудования, кВт | E9: 0.35 | F9: Название материала | G9: PETG-NIT-W4
A10: Ежемесячная сумма амортизации, ₽ | B10: =B9/12 -> 1318.1667
A11: Ежедневная сумма амортизации, ₽ | B11: =B10/30 -> 43.938889 | D11: Стоимость 3d моделей (дизайн + готовые модели) | E11: =E7*G3*1440/60+E8 -> 0 | F11: Стоимость работ | G11: =E11+E12+E13 -> 116.66667
A12: Амортизация в час (8 часовая смена), ₽ | B12: =B11/8 -> 5.4923611 | D12: Стомость оператора | E12: =E6*G4*1440/60 -> 16.666667
A13: Амортизация в минуту (8 часовая смена), ₽ | B13: =B12/60 -> 0.091539352 | D13: Стоимость постобработки | E13: =E6*G6*1440/60 -> 100
A14: Линейный способ расчёта амортизационной стоимости | D14: Стоимость электроэнергии на печать | E14: =E3*E9*G5*1440/60 -> 9.6428617 | F14: Электроэнергия + пластик + амортизация | G14: =E14+E15+E16 -> 152.08607
D15: Стоимость материала для печати (по весу) | E15: =E4/1000*G7 -> 117.26311
A16: Дата начала эксплуатации | B16: 45611 | D16: Амортизация | E16: =B19*G5+1440/60 -> 25.180099
A17: Дата конца эксплуатации | B17: 46751 | D17: Себестоимость | E17: =E16+E15+E14+E13+E12+E11+E5 -> 318.75274
A18: Рабочих часов за время эксплуатации | B18: =NETWORKDAYS(B16,B17,)*8 -> 6520 | D18: Итоговая стоимость с наценкой + допы | G18: =E17+E17*B1+E17*B2+B3+B4+B5 -> 785.31839
A19: Упрощенная амортизация (за час работы), ₽ | B19: =1/B18*B6 -> 7.2782209
A20: Упрощенная амортизация (за минуту работы), ₽ | B20: =B19/60 -> 0.12130368
A21: Пропорциональный способ расчёта амортизации. Если считать, что принтер способен работать 8 часов в день по 5 дней в неделю. Получается примерно 2000 часов в год. Тогда амортизация за час работы будет 1/2000 в расчёте на один год. Если срок полезного использования 3 года то 1/6000 соответственно.
A23: Серые поля заполняем индивидуально, зеленые расчитываются автоматически. Желтые поля выбираем из списка.

Sheet Материалы
A1: Материал | B1: Стоимость | C1: Дата покупки | D1: Плотность | F1: Плотность по умолчанию 1,27
A2: PETG-NIT-W3 | B2: 965 | C2: 45741 | D2: 1.24 | F2: Плотность вариативная 1,24
A3: PETG-StarPlast-G1 | B3: 916 | C3: 45691 | D3: 1.27
A4: PETG-StarPlast-B1 | B4: 969 | C4: 45691 | D4: 1.27
A5: PETG-NIT-W2 | B5: 790 | C5: 45666 | D5: 1.27
A6: PETG-NIT-W1 | B6: 826 | C6: 45641 | D6: 1.27
A7: PETG-NIT-B1 | B7: 796 | C7: 45641 | D7: 1.27
A8: PETG-123D-B1 | B8: 540 | C8: 45625 | D8: 1.27
A9: PLA-CR-W1 | B9: 0 | C9: 45611 | D9: 1.27
A10: PETG-NIT-B2 | B10: 865 | C10: 45760 | D10: 1.27
A11: PLA-CR-W2 | B11: 1000 | D11: 1.27
A12: PETG-NIT-W4 | B12: 869 | C12: 45990 | D12: 1.27
A13: PETG-NIT-B3 | B13: 694 | C13: 45990 | D13: 1.27
A14: PETG-NIT-BLUE1 | B14: 794 | C14: 45990 | D14: 1.27
A15: PETG-NIT-B4 | B15: 865 | C15: 45757 | D15: 1.27
A16: PETG-NIT-B5 | D16: 1.27

Sheet print_history
A1: filename | B1: type | C1: status | D1: start_time | E1: end_time | F1: print_duration | G1: total_duration | H1: filament_used | I1: Общее время | J1: Длина пластика | K1: Вес пластика | L1: Примечание | M1: Себмстоимость | N1: Цена
A2: seed-planter_1x3_PETG_NIT-W4_0.20mm Standard @Creality K1C my_2h4m.gcode | B2: job | C2: completed | D2: 46090.742 | E2: 46090.826 | F2: 6829 | G2: 7209 | H2: 26141.233 | I2: =G2/86400 -> 0.0834375 | J2: =H2/1000 -> 26.141233 | K2: =1.23*PI()*(1.75/2)^2*H2/1000 -> 77.338752
A3: крепление крючка_PETG_NIT-W4_0.12mm Fine_5m26s.gcode | B3: job | C3: completed | D3: 46090.708 | E3: 46090.716 | F3: 360 | G3: 687 | H3: 571.255 | I3: =G3/86400 -> 0.0079513889 | J3: =H3/1000 -> 0.571255 | K3: =1.23*PI()*(1.75/2)^2*H3/1000 -> 1.690056
A4: self-watering-pot-pot-100-x-100-x-100-mm_PETG_NIT-B4_0.20mm Standard 100 quality_3h8m.gcode | B4: job | C4: completed | D4: 46082.525 | E4: 46082.659 | F4: 11274 | G4: 11611 | H4: 28900.368 | I4: =G4/86400 -> 0.13438657 | J4: =H4/1000 -> 28.900368 | K4: =1.23*PI()*(1.75/2)^2*H4/1000 -> 85.501644
A5: self-watering-pot-base-100-x-100-mm_PETG_NIT-B4_0.20mm Standard 150_1h34m.gcode | B5: job | C5: completed | D5: 46082.442 | E5: 46082.506 | F5: 5086 | G5: 5486 | H5: 18878.802 | I5: =G5/86400 -> 0.06349537 | J5: =H5/1000 -> 18.878802 | K5: =1.23*PI()*(1.75/2)^2*H5/1000 -> 55.852874
A6: Bottom - 0.4 PETG-PC_PETG_NIT-B3_0.20mm Standard 150_31m51s.gcode | B6: job | C6: completed | D6: 46081.938 | E6: 46081.966 | F6: 1976 | G6: 2401 | H6: 3809.439 | I6: =G6/86400 -> 0.027789352 | J6: =H6/1000 -> 3.809439 | K6: =1.23*PI()*(1.75/2)^2*H6/1000 -> 11.270213
A7: adapter_PETG_NIT-B3_0.20mm Standard 120_19m48s.gcode | B7: job | C7: completed | D7: 46081.906 | E7: 46081.924 | F7: 1183 | G7: 1539 | H7: 3049.159 | I7: =G7/86400 -> 0.0178125 | J7: =H7/1000 -> 3.049159 | K7: =1.23*PI()*(1.75/2)^2*H7/1000 -> 9.0209269
A8: stone_holder_wusthof_PETG_NIT-B3_0.20mm Standard 120_53m10s.gcode | B8: job | C8: completed | D8: 46061.467 | E8: 46061.506 | F8: 2998 | G8: 3362 | H8: 6280.199 | I8: =G8/86400 -> 0.038912037 | J8: =H8/1000 -> 6.280199 | K8: =1.23*PI()*(1.75/2)^2*H8/1000 -> 18.579948
A9: stone_holder_wusthof_NIT-PETG-B3_42m56s.gcode | B9: job | C9: completed | D9: 46054.522 | E9: 46054.554 | F9: 2460 | G9: 2779 | H9: 5948.623 | I9: =G9/86400 -> 0.032164352 | J9: =H9/1000 -> 5.948623 | K9: =1.23*PI()*(1.75/2)^2*H9/1000 -> 17.598982
A10: knife-sharpener_NIT-PETG-B3_3h54m.gcode | B10: job | C10: completed | D10: 46053.629 | E10: 46053.792 | F10: 13564 | G10: 14009 | H10: 45611.101 | I10: =G10/86400 -> 0.1621412 | J10: =H10/1000 -> 45.611101 | K10: =1.23*PI()*(1.75/2)^2*H10/1000 -> 134.94029
A11: circle_75_PETG_35m28s.gcode | B11: job | C11: completed | D11: 46034.915 | E11: 46034.945 | F11: 2165 | G11: 2633 | H11: 9113.253 | I11: =G11/86400 -> 0.030474537 | J11: =H11/1000 -> 9.113253 | K11: =1.23*PI()*(1.75/2)^2*H11/1000 -> 26.961529
A12: gridfinity-pult_PETG_NIT-B3_0.20mm Standard 120_38m39s.gcode | B12: job | C12: completed | D12: 46029.426 | E12: 46029.456 | F12: 2194 | G12: 2512 | H12: 6056.881 | I12: =G12/86400 -> 0.029074074 | J12: =H12/1000 -> 6.056881 | K12: =1.23*PI()*(1.75/2)^2*H12/1000 -> 17.919262
A13: gridfinity-2x1-usb-c-microsd-v7_PETG_NIT-B3_0.20mm Standard 120_1h5m.gcode | B13: job | C13: completed | D13: 46027.881 | E13: 46027.931 | F13: 3937 | G13: 4264 | H13: 9101.044 | I13: =G13/86400 -> 0.049351852 | J13: =H13/1000 -> 9.101044 | K13: =1.23*PI()*(1.75/2)^2*H13/1000 -> 26.925409
... A103: Duct_PETG_STARPLAST_0.16mm Optimal 150_2h50m.gcode | B103: job | C103: completed | D103: 45762.817 | E103: 45762.941 | F103: 10266 | G103: 10683 | H103: 22027.653 | I103: =G103/86400 -> 0.12364583 | J103: =H103/1000 -> 22.027653 | K103: =1.23*PI()*(1.75/2)^2*H103/1000 -> 65.168739
A104: 14-khz-whistle_PETG_STARPLAST_0.16mm Optimal 150_21m4s.gcode | B104: job | C104: completed | D104: 45760.742 | E104: 45760.76 | F104: 1300 | G104: 1618 | H104: 1707.364 | I104: =G104/86400 -> 0.018726852 | J104: =H104/1000 -> 1.707364 | K104: =1.23*PI()*(1.75/2)^2*H104/1000 -> 5.0512308 | L104: свисток на 14 кГц
A105: pressure_advance_test_PETG_STARPLAST_0.16mm Optimal 150_6m56s.gcode | B105: job | C105: completed | D105: 45760.728 | E105: 45760.738 | F105: 454 | G105: 887 | H105: 484.901 | I105: =G105/86400 -> 0.010266204 | J105: =H105/1000 -> 0.484901 | K105: =1.23*PI()*(1.75/2)^2*H105/1000 -> 1.434578 | L105: тест
A106: 38.4mm1cyl_valve_PETG_STARPLAST_0.16mm Optimal 150_48m19s.gcode | B106: job | C106: completed | D106: 45760.686 | E106: 45760.724 | F106: 2979 | G106: 3303 | H106: 4749.244 | I106: =G106/86400 -> 0.038229167 | J106: =H106/1000 -> 4.749244 | K106: =1.23*PI()*(1.75/2)^2*H106/1000 -> 14.050623 | L106: лего перегородки 3 шт
A107: Base_PETG_STARPLAST_0.16mm Optimal 150_2h5m.gcode | B107: job | C107: completed | D107: 45760.519 | E107: 45760.611 | F107: 7563 | G107: 7938 | H107: 12215.724 | I107: =G107/86400 -> 0.091875 | J107: =H107/1000 -> 12.215724 | K107: =1.23*PI()*(1.75/2)^2*H107/1000 -> 36.140179 | L107: база на углесос удачный
A108: Base_PETG_STARPLAST_0.16mm Optimal 150_2h3m.gcode | B108: job | C108: completed | D108: 45760.387 | E108: 45760.496 | F108: 9073 | G108: 9436 | H108: 14540.585 | I108: =G108/86400 -> 0.10921296 | J108: =H108/1000 -> 14.540585 | K108: =1.23*PI()*(1.75/2)^2*H108/1000 -> 43.018273 | L108: база на углесос косячный
A109: Cover_PETG_STARPLAST_0.16mm Optimal 150_1h6m.gcode | B109: job | C109: completed | D109: 45759.902 | E109: 45759.953 | F109: 3996 | G109: 4433 | H109: 9320.64 | I109: =G109/86400 -> 0.05130787 | J109: =H109/1000 -> 9.32064 | K109: =1.23*PI()*(1.75/2)^2*H109/1000 -> 27.575083 | L109: крышка на углесос
A110: Cover_PETG_STARPLAST_0.16mm Optimal 150_1h6m.gcode | B110: job | C110: klippy_disconnect | D110: 45759.9 | E110: 45759.901 | F110: 0 | G110: 26 | H110: 0 | I110: =G110/86400 -> 0.00030092593 | J110: =H110/1000 -> 0 | K110: =1.23*PI()*(1.75/2)^2*H110/1000 -> 0
A111: 38.4mm1cyl_valve_PETG_STARPLAST_0.16mm Optimal 150_15m18s.gcode | B111: job | C111: completed | D111: 45759.878 | E111: 45759.892 | F111: 978 | G111: 1285 | H111: 1606.007 | I111: =G111/86400 -> 0.014872685 | J111: =H111/1000 -> 1.606007 | K111: =1.23*PI()*(1.75/2)^2*H111/1000 -> 4.7513664 | L111: лего перегородка 1 шт
A112: OrcaCube_PETG_StarPlast-B1_0.20mm Standard 120_39m19s.gcode | B112: job | C112: completed | D112: 45759.758 | E112: 45759.787 | F112: 2254 | G112: 2582 | H112: 4218.788 | I112: =G112/86400 -> 0.029884259 | J112: =H112/1000 -> 4.218788 | K112: =1.23*PI()*(1.75/2)^2*H112/1000 -> 12.48127 | L112: тест орка кубик
A113: Base_PETG_STARPLAST_0.16mm Optimal 150_1h58m.gcode | B113: job | C113: cancelled | D113: 45759.581 | E113: 45759.63 | F113: 3792 | G113: 4187 | H113: 9419.558 | I113: =G113/86400 -> 0.048460648 | J113: =H113/1000 -> 9.419558 | K113: =1.23*PI()*(1.75/2)^2*H113/1000 -> 27.867731 | L113: база на углесос косячный
A114: K1_best_5015_blower_remix_2025_PETG_STARPLAST_0.16mm Optimal 150_2h14m.gcode | B114: job | C114: completed | D114: 45759.409 | E114: 45759.505 | F114: 7939 | G114: 8301 | H114: 6963.853 | I114: =G114/86400 -> 0.096076389 | J114: =H114/1000 -> 6.963853 | K114: =1.23*PI()*(1.75/2)^2*H114/1000 -> 20.602536 | L114: держатель дуйки 5015 ремикс 2025
A115: Base cover_PETG_STARPLAST_0.16mm Optimal 150_38m58s.gcode | B115: job | C115: completed | D115: 45758.927 | E115: 45758.958 | F115: 2335 | G115: 2708 | H115: 5274.29 | I115: =G115/86400 -> 0.031342593 | J115: =H115/1000 -> 5.27429 | K115: =1.23*PI()*(1.75/2)^2*H115/1000 -> 15.60397 | L115: крышка на базу углесоса
A116: Base_PETG_STARPLAST_0.16mm Optimal 150_1h45m.gcode | B116: job | C116: cancelled | D116: 45758.76 | E116: 45758.804 | F116: 3322 | G116: 3760 | H116: 9187.06 | I116: =G116/86400 -> 0.043518519 | J116: =H116/1000 -> 9.18706 | K116: =1.23*PI()*(1.75/2)^2*H116/1000 -> 27.179887 | L116: база на углесос косячный
A117: peglock_board_attachment_PETG_STARPLAST_0.20mm Standard 150_14m2s.gcode | B117: job | C117: completed | D117: 45757.946 | E117: 45757.959 | F117: 833 | G117: 1119 | H117: 1339.844 | I117: =G117/86400 -> 0.012951389 | J117: =H117/1000 -> 1.339844 | K117: =1.23*PI()*(1.75/2)^2*H117/1000 -> 3.9639241 | L117: пеглок 2 шт
A118: temperature_tower_PETG_STARPLAST_0.20mm Standard 150_45m24s.gcode | B118: job | C118: completed | D118: 45757.887 | E118: 45757.923 | F118: 2819 | G118: 3123 | H118: 2946.269 | I118: =G118/86400 -> 0.036145833 | J118: =H118/1000 -> 2.946269 | K118: =1.23*PI()*(1.75/2)^2*H118/1000 -> 8.7165271 | L118: тест
A119: Base_PETG_STARPLAST_0.20mm Standard 150_1h33m.gcode | B119: job | C119: completed | D119: 45757.813 | E119: 45757.878 | F119: 5197 | G119: 5576 | H119: 14250.53 | I119: =G119/86400 -> 0.064537037 | J119: =H119/1000 -> 14.25053 | K119: =1.23*PI()*(1.75/2)^2*H119/1000 -> 42.160146 | L119: база на углесос косячный
A120: 14-khz-whistle_PETG_STARPLAST_0.16mm Optimal 150_18m25s.gcode | B120: job | C120: completed | D120: 45756.903 | E120: 45756.92 | F120: 1130 | G120: 1460 | H120: 2272.09 | I120: =G120/86400 -> 0.016898148 | J120: =H120/1000 -> 2.27209 | K120: =1.23*PI()*(1.75/2)^2*H120/1000 -> 6.7219708 | L120: свисток на 14 кГц косячный
A121: gridfinity-standalone-base-4x4_PETG_STARPLAST_0.20mm Standard 150_1h47m.gcode | B121: job | C121: completed | D121: 45756.792 | E121: 45756.867 | F121: 6022 | G121: 6481 | H121: 16394.202 | I121: =G121/86400 -> 0.075011574 | J121: =H121/1000 -> 16.394202 | K121: =1.23*PI()*(1.75/2)^2*H121/1000 -> 48.502193 | L121: база гридфинити 4×4 настольная
A122: Pegboard gridfinity 1x3 shorter_PETG_STARPLAST_0.16mm Optimal 230_1h22m.gcode | B122: job | C122: completed | D122: 45754.878 | E122: 45754.938 | F122: 4841 | G122: 5204 | H122: 8585.841 | I122: =G122/86400 -> 0.060231481 | J122: =H122/1000 -> 8.585841 | K122: =1.23*PI()*(1.75/2)^2*H122/1000 -> 25.401182 | L122: гридфинити держатель на пегборду 1×3
... A141: Planter _PETG_STARPLAST_0.20mm Standard 150_1h46m.gcode | B141: job | C141: completed | D141: 45739.784 | E141: 45739.862 | F141: 6398 | G141: 6734 | H141: 22359.01 | I141: =G141/86400 -> 0.077939815 | J141: =H141/1000 -> 22.35901 | K141: =1.23*PI()*(1.75/2)^2*H141/1000 -> 66.149057 | L141: горшочек
A142: cable_clips_PETG_STARPLAST_0.16mm Optimal_1h7m.gcode | B142: job | C142: completed | D142: 45738.899 | E142: 45738.946 | F142: 3678 | G142: 4031 | H142: 8428.36 | I142: =G142/86400 -> 0.046655093 | J142: =H142/1000 -> 8.42836 | K142: =1.23*PI()*(1.75/2)^2*H142/1000 -> 24.935275
A143: cable_clip_14mm_PETG_STARPLAST_0.16mm Optimal_6m39s.gcode | B143: job | C143: completed | D143: 45738.878 | E143: 45738.887 | F143: 362 | G143: 692 | H143: 682.517 | I143: =G143/86400 -> 0.0080092593 | J143: =H143/1000 -> 0.682517 | K143: =1.23*PI()*(1.75/2)^2*H143/1000 -> 2.0192243
A144: SpeedTestStructure_PETG_STARPLAST_0.20mm Standard 150_14m7s.gcode | B144: job | C144: completed | D144: 45738.773 | E144: 45738.787 | F144: 879 | G144: 1302 | H144: 3627.235 | I144: =G144/86400 -> 0.015069444 | J144: =H144/1000 -> 3.627235 | K144: =1.23*PI()*(1.75/2)^2*H144/1000 -> 10.731163
A145: VFA_PETG_STARPLAST_0.20mm Standard_53m24s.gcode | B145: job | C145: completed | D145: 45738.692 | E145: 45738.733 | F145: 3148 | G145: 3525 | H145: 9143.981 | I145: =G145/86400 -> 0.040798611 | J145: =H145/1000 -> 9.143981 | K145: =1.23*PI()*(1.75/2)^2*H145/1000 -> 27.052438
A146: OrcaToleranceTest_PETG_STARPLAST_0.16mm Optimal_10m32s.gcode | B146: job | C146: completed | D146: 45733.942 | E146: 45733.953 | F146: 655 | G146: 970 | H146: 1015.998 | I146: =G146/86400 -> 0.011226852 | J146: =H146/1000 -> 1.015998 | K146: =1.23*PI()*(1.75/2)^2*H146/1000 -> 3.0058267
A147: pressure_advance_test_PETG_STARPLAST_0.16mm Optimal_3m21s.gcode | B147: job | C147: completed | D147: 45733.931 | E147: 45733.938 | F147: 233 | G147: 656 | H147: 256.732 | I147: =G147/86400 -> 0.0075925926 | J147: =H147/1000 -> 0.256732 | K147: =1.23*PI()*(1.75/2)^2*H147/1000 -> 0.75954078
A148: pressure_advance_test_PETG_STARPLAST_0.16mm Optimal_6m37s.gcode | B148: job | C148: completed | D148: 45733.917 | E148: 45733.928 | F148: 434 | G148: 871 | H148: 487.952 | I148: =G148/86400 -> 0.010081019 | J148: =H148/1000 -> 0.487952 | K148: =1.23*PI()*(1.75/2)^2*H148/1000 -> 1.4436044
A149: 28mm-Bolt-for-Tilt-Adjustment_PETG_STARPLAST_0.16mm Optimal_3h34m.gcode | B149: job | C149: completed | D149: 45732.665 | E149: 45732.816 | F149: 12275 | G149: 13100 | H149: 25742.605 | I149: =G149/86400 -> 0.15162037 | J149: =H149/1000 -> 25.742605 | K149: =1.23*PI()*(1.75/2)^2*H149/1000 -> 76.159412
A150: Watering Can_PETG_STARPLAST_0.20mm Standard_3h51m.gcode | B150: job | C150: completed | D150: 45732.492 | E150: 45732.654 | F150: 13511 | G150: 13982 | H150: 39812.05 | I150: =G150/86400 -> 0.1618287 | J150: =H150/1000 -> 39.81205 | K150: =1.23*PI()*(1.75/2)^2*H150/1000 -> 117.78382
A151: gridfinity_ultralightbin_plainedition_2x2x5_PETG_STARPLAST_0.20mm Standard_47m44s.gcode | B151: job | C151: completed | D151: 45730.799 | E151: 45730.836 | F151: 2837 | G151: 3197 | H151: 7843.067 | I151: =G151/86400 -> 0.037002315 | J151: =H151/1000 -> 7.843067 | K151: =1.23*PI()*(1.75/2)^2*H151/1000 -> 23.203688
A152: gridfinity_ultralightbin_plainedition_2x4x5_PETG_STARPLAST_0.20mm Standard_1h20m.gcode | B152: job | C152: completed | D152: 45729.799 | E152: 45729.86 | F152: 4797 | G152: 5247 | H152: 13596.717 | I152: =G152/86400 -> 0.060729167 | J152: =H152/1000 -> 13.596717 | K152: =1.23*PI()*(1.75/2)^2*H152/1000 -> 40.225842
A153: gridfinity-standalone-base-4x4_PETG_STARPLAST_0.20mm Standart low speed_1h55m.gcode | B153: job | C153: completed | D153: 45728.831 | E153: 45728.915 | F153: 6774 | G153: 7246 | H153: 18326.821 | I153: =G153/86400 -> 0.083865741 | J153: =H153/1000 -> 18.326821 | K153: =1.23*PI()*(1.75/2)^2*H153/1000 -> 54.21984
... A156: skadis-board-200x200_PETG_STARPLAST_0.16mm Optimal low speed_3h42m.gcode | B156: job | C156: completed | D156: 45724.742 | E156: 45724.894 | F156: 12616 | G156: 13101 | H156: 18848.394 | I156: =G156/86400 -> 0.15163194 | J156: =H156/1000 -> 18.848394 | K156: =1.23*PI()*(1.75/2)^2*H156/1000 -> 55.762912
A157: postmark_60x70_PETG_STARPLAST_0.16mm Optimal low speed_27m35s.gcode | B157: job | C157: completed | D157: 45722.861 | E157: 45722.883 | F157: 1622 | G157: 1950 | H157: 3512.067 | I157: =G157/86400 -> 0.022569444 | J157: =H157/1000 -> 3.512067 | K157: =1.23*PI()*(1.75/2)^2*H157/1000 -> 10.390439 | L157: Форма «марка»
A158: bird_2_PETG_STARPLAST_0.16mm Optimal low speed_50m29s.gcode | B158: job | C158: completed | D158: 45722.797 | E158: 45722.836 | F158: 2993 | G158: 3356 | H158: 6421.948 | I158: =G158/86400 -> 0.038842593 | J158: =H158/1000 -> 6.421948 | K158: =1.23*PI()*(1.75/2)^2*H158/1000 -> 18.999312 | L158: Форма «Птички-2» 2шт
A159: bird_3_PETG_STARPLAST_0.16mm Optimal low speed_29m21s.gcode | B159: job | C159: completed | D159: 45721.925 | E159: 45721.949 | F159: 1777 | G159: 2091 | H159: 4099.236 | I159: =G159/86400 -> 0.024201389 | J159: =H159/1000 -> 4.099236 | K159: =1.23*PI()*(1.75/2)^2*H159/1000 -> 12.127576 | L159: Форма «Птички-3»
A160: bird_1_PETG_STARPLAST_0.16mm Optimal low speed_28m50s.gcode | B160: job | C160: completed | D160: 45721.899 | E160: 45721.923 | F160: 1700 | G160: 2059 | H160: 3342.973 | I160: =G160/86400 -> 0.023831019 | J160: =H160/1000 -> 3.342973 | K160: =1.23*PI()*(1.75/2)^2*H160/1000 -> 9.8901746 | L160: Форма «Птички-1»
A161: Chip_Bag_Clip_V7_Medium_PETG-StarPlast-G1_0.16mm Optimal low speed_1h11m.gcode | B161: job | C161: completed | D161: 45718.833 | E161: 45718.885 | F161: 4175 | G161: 4527 | H161: 6565.051 | I161: =G161/86400 -> 0.052395833 | J161: =H161/1000 -> 6.565051 | K161: =1.23*PI()*(1.75/2)^2*H161/1000 -> 19.422682 | L161: Большие клипсы на пакет угля 2 шт
A162: 20-cm-side-a_PETG_STARPLAST-G1_0.16mm Optimal low speed_28m23s.gcode | B162: job | C162: completed | D162: 45717.788 | E162: 45717.812 | F162: 1712 | G162: 2037 | H162: 3456.926 | I162: =G162/86400 -> 0.023576389 | J162: =H162/1000 -> 3.456926 | K162: =1.23*PI()*(1.75/2)^2*H162/1000 -> 10.227304 | L162: Фастекс
A163: skadis-board-mount-tool_PETG_STARPLAST-G1_0.16mm Optimal low speed_27m5s.gcode | B163: job | C163: completed | D163: 45717.758 | E163: 45717.78 | F163: 1583 | G163: 1915 | H163: 2748.036 | I163: =G163/86400 -> 0.022164352 | J163: =H163/1000 -> 2.748036 | K163: =1.23*PI()*(1.75/2)^2*H163/1000 -> 8.1300555
A164: skadis-board-mount-tool_PETG_STARPLAST-G1_0.20mm Standart low speed_22m8s.gcode | B164: job | C164: completed | D164: 45717.713 | E164: 45717.732 | F164: 1281 | G164: 1603 | H164: 2857.182 | I164: =G164/86400 -> 0.018553241 | J164: =H164/1000 -> 2.857182 | K164: =1.23*PI()*(1.75/2)^2*H164/1000 -> 8.4529635
A165: skadis-board-160x160_PETG_NIT-W2_0.20mm Standart low speed_1h52m.gcode | B165: job | C165: completed | D165: 45717.621 | E165: 45717.703 | F165: 6413 | G165: 7117 | H165: 13455.605 | I165: =G165/86400 -> 0.082372685 | J165: =H165/1000 -> 13.455605 | K165: =1.23*PI()*(1.75/2)^2*H165/1000 -> 39.808363
A166: skadis-board-160x160_PETG_NIT-W1_0.16mm Optimal_2h33m.gcode | B166: job | C166: completed | D166: 45717.492 | E166: 45717.609 | F166: 9245 | G166: 10061 | H166: 13494.194 | I166: =G166/86400 -> 0.11644676 | J166: =H166/1000 -> 13.494194 | K166: =1.23*PI()*(1.75/2)^2*H166/1000 -> 39.922529
A167: PA-shablon_PETG_NIT-W1_0.16mm Optimal_7m39s.gcode | B167: job | C167: completed | D167: 45716.885 | E167: 45716.896 | F167: 523 | G167: 947 | H167: 693.098 | I167: =G167/86400 -> 0.010960648 | J167: =H167/1000 -> 0.693098 | K167: =1.23*PI()*(1.75/2)^2*H167/1000 -> 2.0505282
A168: skadis-board-160x160_PETG_NIT-W1_0.16mm Optimal_2h30m.gcode | B168: job | C168: completed | D168: 45716.747 | E168: 45716.858 | F168: 9185 | G168: 9587 | H168: 13494.184 | I168: =G168/86400 -> 0.11096065 | J168: =H168/1000 -> 13.494184 | K168: =1.23*PI()*(1.75/2)^2*H168/1000 -> 39.922499
A169: 3dpen-holder-peglock_PETG_NIT-W1_0.16mm Optimal_48m18s.gcode | B169: job | C169: completed | D169: 45715.843 | E169: 45715.881 | F169: 2931 | G169: 3267 | H169: 5660.304 | I169: =G169/86400 -> 0.0378125 | J169: =H169/1000 -> 5.660304 | K169: =1.23*PI()*(1.75/2)^2*H169/1000 -> 16.745991
A170: gridfinity_ultralightbin_plainedition_1x3x2_PETG_NIT-W1_0.16mm Optimal_28m15s.gcode | B170: job | C170: completed | D170: 45714.903 | E170: 45714.927 | F170: 1682 | G170: 2053 | H170: 4451.892 | I170: =G170/86400 -> 0.023761574 | J170: =H170/1000 -> 4.451892 | K170: =1.23*PI()*(1.75/2)^2*H170/1000 -> 13.170908
A171: flow-calibration-for-flexis-v4-no-inst-by-ck3d_PETG_NIT-W1_0.16mm Optimal_15m23s.gcode | B171: job | C171: completed | D171: 45713.927 | E171: 45713.941 | F171: 934 | G171: 1249 | H171: 1317.567 | I171: =G171/86400 -> 0.014456019 | J171: =H171/1000 -> 1.317567 | K171: =1.23*PI()*(1.75/2)^2*H171/1000 -> 3.8980176
A172: Skadis_Universal_Hook_PETG_NIT-W1_0.16mm Optimal_7m18s.gcode | B172: job | C172: completed | D172: 45713.914 | E172: 45713.923 | F172: 439 | G172: 789 | H172: 789.598 | I172: =G172/86400 -> 0.0091319444 | J172: =H172/1000 -> 0.789598 | K172: =1.23*PI()*(1.75/2)^2*H172/1000 -> 2.3360231
A173: flow-calibration-for-flexis-v4-no-inst-by-ck3d_PETG_NIT-W1_0.16mm Optimal_15m24s.gcode | B173: job | C173: completed | D173: 45713.899 | E173: 45713.914 | F173: 936 | G173: 1244 | H173: 1359.693 | I173: =G173/86400 -> 0.014398148 | J173: =H173/1000 -> 1.359693 | K173: =1.23*PI()*(1.75/2)^2*H173/1000 -> 4.0226473
A174: Skadis-gridfinity-with-hooks_PETG_NIT-W1_0.16mm Optimal_59m20s.gcode | B174: job | C174: completed | D174: 45713.847 | E174: 45713.892 | F174: 3463 | G174: 3875 | H174: 7253.334 | I174: =G174/86400 -> 0.044849537 | J174: =H174/1000 -> 7.253334 | K174: =1.23*PI()*(1.75/2)^2*H174/1000 -> 21.458965
... A176: headphone_hook_skadis_PETG_NIT-W1_0.16mm Optimal_58m30s.gcode | B176: job | C176: completed | D176: 45712.799 | E176: 45712.842 | F176: 3429 | G176: 3758 | H176: 5104.547 | I176: =G176/86400 -> 0.04349537 | J176: =H176/1000 -> 5.104547 | K176: =1.23*PI()*(1.75/2)^2*H176/1000 -> 15.101785
A177: skadis-board-200x200_PETG_NIT_0.20mm Standart low speed_2h30m.gcode | B177: job | C177: completed | D177: 45711.847 | E177: 45711.95 | F177: 8470 | G177: 8907 | H177: 17620.686 | I177: =G177/86400 -> 0.10309028 | J177: =H177/1000 -> 17.620686 | K177: =1.23*PI()*(1.75/2)^2*H177/1000 -> 52.130742 | L177: Скадис 200x200
A178: peglock_box_050x100deep2_PETG_StarPlast-G1_0.20mm Standart low speed_1h13m.gcode | B178: job | C178: completed | D178: 45711.76 | E178: 45711.814 | F178: 4347 | G178: 4664 | H178: 12228.97 | I178: =G178/86400 -> 0.053981481 | J178: =H178/1000 -> 12.22897 | K178: =1.23*PI()*(1.75/2)^2*H178/1000 -> 36.179367
A179: peglock_box_100_PETG_StarPlast-G1_0.20mm Standart low speed_1h25m.gcode | B179: job | C179: completed | D179: 45711.634 | E179: 45711.696 | F179: 4986 | G179: 5312 | H179: 13305.727 | I179: =G179/86400 -> 0.061481481 | J179: =H179/1000 -> 13.305727 | K179: =1.23*PI()*(1.75/2)^2*H179/1000 -> 39.36495
A180: flow-calibration-for-flexis-v4-no-inst-by-ck3d_PETG_StarPlast-G1_0.20mm Standart low speed_13m34s.gcode | B180: job | C180: completed | D180: 45711.613 | E180: 45711.626 | F180: 829 | G180: 1140 | H180: 1279.737 | I180: =G180/86400 -> 0.013194444 | J180: =H180/1000 -> 1.279737 | K180: =1.23*PI()*(1.75/2)^2*H180/1000 -> 3.7860977
A181: flow-calibration-for-flexis-v4-no-inst-by-ck3d_PETG_StarPlast-G1_0.20mm Standart low speed_13m34s.gcode | B181: job | C181: completed | D181: 45711.594 | E181: 45711.608 | F181: 829 | G181: 1162 | H181: 1320.621 | I181: =G181/86400 -> 0.013449074 | J181: =H181/1000 -> 1.320621 | K181: =1.23*PI()*(1.75/2)^2*H181/1000 -> 3.9070529
A182: PA_PETG_StarPlast-G1_0.16mm Optimal_7m44s.gcode | B182: job | C182: completed | D182: 45710.928 | E182: 45710.94 | F182: 529 | G182: 992 | H182: 716.716 | I182: =G182/86400 -> 0.011481481 | J182: =H182/1000 -> 0.716716 | K182: =1.23*PI()*(1.75/2)^2*H182/1000 -> 2.1204019
A183: gridfinity-adapter-2x2-1x1-2x1_PETG_StarPlast-G1_0.16mm Optimal_1h37m.gcode | B183: job | C183: completed | D183: 45710.826 | E183: 45710.895 | F183: 5513 | G183: 5948 | H183: 12207.709 | I183: =G183/86400 -> 0.068842593 | J183: =H183/1000 -> 12.207709 | K183: =1.23*PI()*(1.75/2)^2*H183/1000 -> 36.116467
A184: gridfinity_ultralightbin_2x2x1_build-plate-cleaner_PETG_StarPlast-G1_0.16mm Optimal low speed_3h38m.gcode | B184: job | C184: completed | D184: 45710.626 | E184: 45710.776 | F184: 12493 | G184: 12912 | H184: 26744.836 | I184: =G184/86400 -> 0.14944444 | J184: =H184/1000 -> 26.744836 | K184: =1.23*PI()*(1.75/2)^2*H184/1000 -> 79.124509
A185: gridfinity_ultralightbin_plainedition_1x4x5_PETG_StarPlast-G1_0.16mm Optimal low speed_55m38s.gcode | B185: job | C185: completed | D185: 45710.559 | E185: 45710.601 | F185: 3298 | G185: 3697 | H185: 9355.042 | I185: =G185/86400 -> 0.042789352 | J185: =H185/1000 -> 9.355042 | K185: =1.23*PI()*(1.75/2)^2*H185/1000 -> 27.676861
A186: strat_roots_pc1_3_PETG_StarPlast-G1_0.16mm Optimal low speed_35m24s.gcode | B186: job | C186: completed | D186: 45710.524 | E186: 45710.549 | F186: 1899 | G186: 2218 | H186: 2518.07 | I186: =G186/86400 -> 0.025671296 | J186: =H186/1000 -> 2.51807 | K186: =1.23*PI()*(1.75/2)^2*H186/1000 -> 7.4497018
A187: OrcaToleranceTest_PETG_StarPlast-G1_0.16mm Optimal low speed_10m58s.gcode | B187: job | C187: completed | D187: 45710.435 | E187: 45710.448 | F187: 719 | G187: 1055 | H187: 1016.124 | I187: =G187/86400 -> 0.012210648 | J187: =H187/1000 -> 1.016124 | K187: =1.23*PI()*(1.75/2)^2*H187/1000 -> 3.0061995
A188: gridfinity_ultralightbin_plainedition_1x2x5.stl_PETG_34m12s.gcode | B188: job | C188: completed | D188: 45709.817 | E188: 45709.842 | F188: 2129 | G188: 2165 | H188: 5206.992 | I188: =G188/86400 -> 0.02505787 | J188: =H188/1000 -> 5.206992 | K188: =1.23*PI()*(1.75/2)^2*H188/1000 -> 15.404869
A189: gridfinity_ultralightbin_plainedition_1x2x5_PETG_StarPlast-G1_0.20mm Standard_24m51s.gcode | B189: job | C189: completed | D189: 45708.901 | E189: 45708.922 | F189: 1506 | G189: 1818 | H189: 5042.141 | I189: =G189/86400 -> 0.021041667 | J189: =H189/1000 -> 5.042141 | K189: =1.23*PI()*(1.75/2)^2*H189/1000 -> 14.917158 | L189: бокс 2x1 гридфинити
A190: peglock_boxes-1x1_100_PETG_StarPlast-G1_0.20mm Standard_2h6m.gcode | B190: job | C190: completed | D190: 45708.787 | E190: 45708.876 | F190: 7296 | G190: 7675 | H190: 25091.038 | I190: =G190/86400 -> 0.088831019 | J190: =H190/1000 -> 25.091038 | K190: =1.23*PI()*(1.75/2)^2*H190/1000 -> 74.231753 | L190: три бокса на пегборду гридфинити
A191: pegboard-lock-vertical_v2_PETG_0.20mm Standard_2m47s.gcode | B191: job | C191: completed | D191: 45707.928 | E191: 45707.935 | F191: 207 | G191: 515 | H191: 382.864 | I191: =G191/86400 -> 0.0059606481 | J191: =H191/1000 -> 0.382864 | K191: =1.23*PI()*(1.75/2)^2*H191/1000 -> 1.1327019 | L191: вертикальный замок на пегборд
A192: 1x2PegMount_PETG_StarPlast-G1_0.20mm Standart low speed_1h31m.gcode | B192: job | C192: completed | D192: 45707.812 | E192: 45707.878 | F192: 5346 | G192: 5732 | H192: 14238.266 | I192: =G192/86400 -> 0.066342593 | J192: =H192/1000 -> 14.238266 | K192: =1.23*PI()*(1.75/2)^2*H192/1000 -> 42.123863
A193: gridfinity-standalone-base-4x4_PETG_StarPlast-G1_0.20mm Standard_1h35m.gcode | B193: job | C193: completed | D193: 45704.74 | E193: 45704.812 | F193: 5641 | G193: 6152 | H193: 16559.915 | I193: =G193/86400 -> 0.071203704 | J193: =H193/1000 -> 16.559915 | K193: =1.23*PI()*(1.75/2)^2*H193/1000 -> 48.992454 | L193: База гридфинити настольная 4x4
A194: Sy's Pegboard gridfinity 1x3 shorter_PETG_NIT-W2_0.20mm Standard_1h47m.gcode | B194: job | C194: completed | D194: 45704.485 | E194: 45704.566 | F194: 6539 | G194: 7022 | H194: 13434.633 | I194: =G194/86400 -> 0.081273148 | J194: =H194/1000 -> 13.434633 | K194: =1.23*PI()*(1.75/2)^2*H194/1000 -> 39.746317 | L194: база гридфинити на доску
A195: peglock_board_attachment_PETG_NIT-W2_0.20mm Standard_10m20s.gcode | B195: job | C195: completed | D195: 45704.44 | E195: 45704.451 | F195: 679 | G195: 1014 | H195: 1163.665 | I195: =G195/86400 -> 0.011736111 | J195: =H195/1000 -> 1.163665 | K195: =1.23*PI()*(1.75/2)^2*H195/1000 -> 3.4426991 | L195: пеглок
A196: 37mm Bottle Holder_PETG-NIT-W2_0.20mm Standard_43m59s.gcode | B196: job | C196: completed | D196: 45703.852 | E196: 45703.885 | F196: 2563 | G196: 2881 | H196: 8127.874 | I196: =G196/86400 -> 0.033344907 | J196: =H196/1000 -> 8.127874 | K196: =1.23*PI()*(1.75/2)^2*H196/1000 -> 24.046288 | L196: держатель дихлорэтана на гридфинити базу
A197: glue-base_2x2base_PETG-NIT-W2_0.20mm Standard_1h9m.gcode | B197: job | C197: completed | D197: 45703.765 | E197: 45703.815 | F197: 4044 | G197: 4409 | H197: 11129.647 | I197: =G197/86400 -> 0.051030093 | J197: =H197/1000 -> 11.129647 | K197: =1.23*PI()*(1.75/2)^2*H197/1000 -> 32.927024 | L197: держатель для клея на гридфинити базу
A198: 2x2x3u-sticky-note-holder_PETG-NIT-W2_0.20mm Standard_1h58m.gcode | B198: job | C198: completed | D198: 45703.634 | E198: 45703.722 | F198: 7187 | G198: 7579 | H198: 20456.457 | I198: =G198/86400 -> 0.087719907 | J198: =H198/1000 -> 20.456457 | K198: =1.23*PI()*(1.75/2)^2*H198/1000 -> 60.520361 | L198: держатель для стикнотов на гридфинити базу
A199: 1x2PegMount_PETG-NIT-W2_0.20mm Standard_1h39m.gcode | B199: job | C199: completed | D199: 45700.811 | E199: 45700.885 | F199: 5969 | G199: 6347 | H199: 17702.598 | I199: =G199/86400 -> 0.073460648 | J199: =H199/1000 -> 17.702598 | K199: =1.23*PI()*(1.75/2)^2*H199/1000 -> 52.373078 | L199: база гридфинити на доску
A200: pegboard-pin_v4_PETG-NIT-W2_0.20mm Standard_6m51s.gcode | B200: job | C200: completed | D200: 45699.872 | E200: 45699.881 | F200: 472 | G200: 786 | H200: 522.989 | I200: =G200/86400 -> 0.0090972222 | J200: =H200/1000 -> 0.522989 | K200: =1.23*PI()*(1.75/2)^2*H200/1000 -> 1.5472612 | L200: пин та пегборду
A201: pegboard-pin_v3_PETG-NIT-W2_0.16mm Optimal low speed_6m15s.gcode | B201: job | C201: completed | D201: 45699.856 | E201: 45699.865 | F201: 434 | G201: 767 | H201: 314.561 | I201: =G201/86400 -> 0.0088773148 | J201: =H201/1000 -> 0.314561 | K201: =1.23*PI()*(1.75/2)^2*H201/1000 -> 0.93062768 | L201: пин на пегборду
A202: pegboard-pin_v2_PETG-NIT-W2_0.16mm Optimal low speed_4m46s.gcode | B202: job | C202: completed | D202: 45698.922 | E202: 45698.931 | F202: 332 | G202: 800 | H202: 372.062 | I202: =G202/86400 -> 0.0092592593 | J202: =H202/1000 -> 0.372062 | K202: =1.23*PI()*(1.75/2)^2*H202/1000 -> 1.1007442 | L202: пин на пегборду
A203: Gridfinity_UltraLightBin_PlainEdition_3x5x10_PETG-NIT-W2_0.20mm Standard speed 200_2h21m.gcode | B203: job | C203: completed | D203: 45698.805 | E203: 45698.908 | F203: 8443 | G203: 8913 | H203: 30286.825 | I203: =G203/86400 -> 0.10315972 | J203: =H203/1000 -> 30.286825 | K203: =1.23*PI()*(1.75/2)^2*H203/1000 -> 89.603472 | L203: Коробка гридфинити 3x5x10 для Ильи Журавлёва
A204: pegboard-pin_v1_PETG-STAR-G1_0.16mm Optimal low speed_5m9s.gcode | B204: job | C204: completed | D204: 45697.917 | E204: 45697.925 | F204: 371 | G204: 679 | H204: 409.283 | I204: =G204/86400 -> 0.0078587963 | J204: =H204/1000 -> 0.409283 | K204: =1.23*PI()*(1.75/2)^2*H204/1000 -> 1.2108624 | L204: пин на пегборду
A205: hook_v1_PETG-STAR-G1_0.16mm Optimal low speed_9m23s.gcode | B205: job | C205: completed | D205: 45697.896 | E205: 45697.906 | F205: 572 | G205: 884 | H205: 781.757 | I205: =G205/86400 -> 0.010231481 | J205: =H205/1000 -> 0.781757 | K205: =1.23*PI()*(1.75/2)^2*H205/1000 -> 2.3128255
A206: hook_v1_PETG-STAR-G1_2m19s.gcode | B206: job | C206: completed | D206: 45697.868 | E206: 45697.874 | F206: 172 | G206: 489 | H206: 230.713 | I206: =G206/86400 -> 0.0056597222 | J206: =H206/1000 -> 0.230713 | K206: =1.23*PI()*(1.75/2)^2*H206/1000 -> 0.68256365
A207: pressure_advance_test.stl_PETG_5m54s.gcode | B207: job | C207: completed | D207: 45696.96 | E207: 45696.966 | F207: 397 | G207: 448 | H207: 595.017 | I207: =G207/86400 -> 0.0051851852 | J207: =H207/1000 -> 0.595017 | K207: =1.23*PI()*(1.75/2)^2*H207/1000 -> 1.7603558
A208: OrcaCube_PETG-STAR-G1_25m0s.gcode | B208: job | C208: completed | D208: 45696.927 | E208: 45696.949 | F208: 1573 | G208: 1891 | H208: 3687.738 | I208: =G208/86400 -> 0.021886574 | J208: =H208/1000 -> 3.687738 | K208: =1.23*PI()*(1.75/2)^2*H208/1000 -> 10.910161
A209: OrcaCube_PETG-STAR-G1_35m39s.gcode | B209: job | C209: completed | D209: 45696.869 | E209: 45696.898 | F209: 2219 | G209: 2550 | H209: 4093.785 | I209: =G209/86400 -> 0.029513889 | J209: =H209/1000 -> 4.093785 | K209: =1.23*PI()*(1.75/2)^2*H209/1000 -> 12.111449
A210: SpeedTestStructure_PETG-STAR-G1_21m1s.gcode | B210: job | C210: cancelled | D210: 45696.847 | E210: 45696.863 | F210: 933 | G210: 1347 | H210: 3941.039 | I210: =G210/86400 -> 0.015590278 | J210: =H210/1000 -> 3.941039 | K210: =1.23*PI()*(1.75/2)^2*H210/1000 -> 11.659551
...
